geogst/__init__.py
geogst/configs/__init__.py
geogst/configs/plots.py
geogst/core/__init__.py
geogst/core/deformations/__init__.py
geogst/core/deformations/space3d/__init__.py
geogst/core/deformations/space3d/deformations.py
geogst/core/deformations/space3d/rotations.py
geogst/core/deformations/space3d/shears.py
geogst/core/geology/__init__.py
geogst/core/geology/base.py
geogst/core/geology/faults.py
geogst/core/geology/ptbaxes.py
geogst/core/geology/utils/__init__.py
geogst/core/geology/utils/faults.py
geogst/core/geology/utils/parsing.py
geogst/core/geology/utils/type_checks.py
geogst/core/geometries/__init__.py
geogst/core/geometries/checks.py
geogst/core/geometries/lines.py
geogst/core/geometries/meshes.py
geogst/core/geometries/planes.py
geogst/core/geometries/points.py
geogst/core/geometries/polygons.py
geogst/core/geometries/reference_frames.py
geogst/core/geometries/shape.py
geogst/core/geometries/georeferencing/__init__.py
geogst/core/geometries/georeferencing/crs.py
geogst/core/geometries/georeferencing/geodetic.py
geogst/core/geometries/georeferencing/geotransform.py
geogst/core/geometries/grids/__init__.py
geogst/core/geometries/grids/intersections.py
geogst/core/geometries/grids/operators.py
geogst/core/geometries/grids/rasters.py
geogst/core/geometries/operators/__init__.py
geogst/core/geometries/operators/transformations.py
geogst/core/inspections/__init__.py
geogst/core/inspections/errors.py
geogst/core/inspections/functions.py
geogst/core/mathematics/__init__.py
geogst/core/mathematics/arrays.py
geogst/core/mathematics/defaults.py
geogst/core/mathematics/quaternions.py
geogst/core/mathematics/statistics.py
geogst/core/mathematics/utils.py
geogst/core/mathematics/vectors2d.py
geogst/core/mathematics/vectors3d.py
geogst/core/orientations/__init__.py
geogst/core/orientations/defaults.py
geogst/core/orientations/orientations.py
geogst/core/orientations/utils.py
geogst/core/profiles/__init__.py
geogst/core/profiles/geoprofiles.py
geogst-1.0.3.dist-info/LICENSE
geogst-1.0.3.dist-info/METADATA
geogst-1.0.3.dist-info/WHEEL
geogst-1.0.3.dist-info/top_level.txt
geogst-1.0.3.dist-info/RECORD
