Metadata-Version: 2.1
Name: geogst
Version: 1.0.3
Summary: geogst is a structural geology module
Home-page: https://gitlab.com/mauroalberti/geogst
Author: Mauro Alberti
Author-email: alberti.m65@gmail.com
License: MIT
Project-URL: Bug Tracker, https://gitlab.com/mauroalberti/geogst/-/issues
Project-URL: Documentation, https://gitlab.com/mauroalberti/geogst/-/blob/main/README.md
Project-URL: Source Code, https://gitlab.com/mauroalberti/geogst/-/tree/main
Classifier: License :: OSI Approved :: MIT License
Classifier: Operating System :: OS Independent
Classifier: Intended Audience :: Developers
Classifier: Intended Audience :: Science/Research
Classifier: Programming Language :: Python :: 3
Classifier: Programming Language :: Python :: 3 :: Only
Classifier: Topic :: Software Development
Classifier: Topic :: Scientific/Engineering :: GIS
Classifier: Topic :: Utilities
Requires-Python: >=3
License-File: LICENSE
Requires-Dist: affine>=2.3.0
Requires-Dist: bokeh>=2.3.1
Requires-Dist: GDAL>=3.3.2
Requires-Dist: geopandas>=0.9.0
Requires-Dist: imageio>=2.9.0
Requires-Dist: matplotlib>=3.4.2
Requires-Dist: mplstereonet>=0.6.2
Requires-Dist: numpy>=1.19.5
Requires-Dist: numtest>=2.0.6
Requires-Dist: ogr>=0.35.0
Requires-Dist: pyproj>=2.5.0
Requires-Dist: PyYAML>=5.3.1
Requires-Dist: scipy
Requires-Dist: setuptools
Requires-Dist: shapely>=1.7.1
